cellular_automaton/__init__.py
cellular_automaton/automaton.py
cellular_automaton/display.py
cellular_automaton/neighborhood.py
cellular_automaton-1.0.8.dist-info/LICENSE.txt
cellular_automaton-1.0.8.dist-info/METADATA
cellular_automaton-1.0.8.dist-info/WHEEL
cellular_automaton-1.0.8.dist-info/top_level.txt
cellular_automaton-1.0.8.dist-info/RECORD
