Metadata-Version: 2.1
Name: cellular-automaton
Version: 1.0.8
Summary: N dimensional cellular automaton.
Home-page: https://gitlab.com/DamKoVosh/cellular_automaton
Author: Richard Feistenauer
Author-email: r.feistenauer@web.de
License: Apache License 2.0
Platform: UNKNOWN
Requires: Python (>3.6.1)
Requires: recordclass
